fastapi_blueprint/__init__.py
fastapi_blueprint/cli.py
fastapi_blueprint/tests/__init__.py
fastapi_blueprint/tests/cli_test.py
fastapi_blueprint/utils/__init__.py
fastapi_blueprint/utils/component.py
fastapi_blueprint/utils/constants.py
fastapi_blueprint/utils/project_structure.py
fastapi_blueprint-1.0.2.dist-info/LICENSE
fastapi_blueprint-1.0.2.dist-info/METADATA
fastapi_blueprint-1.0.2.dist-info/WHEEL
fastapi_blueprint-1.0.2.dist-info/entry_points.txt
fastapi_blueprint-1.0.2.dist-info/top_level.txt
fastapi_blueprint-1.0.2.dist-info/RECORD
