Metadata-Version: 2.1
Name: fastapi_blueprint
Version: 1.0.2
Summary: A CLI tool to generate file structure for FastAPI projects.
Author: Sadegh Ranjbar
Author-email: sadegh.r1404@gmail.com
Classifier: Programming Language :: Python :: 3
Classifier: License :: OSI Approved :: MIT License
Requires-Python: >=3.6
License-File: LICENSE
